{
  "gitSyncId": "67f9f911f36c48005daec8a8_6d768ef9-20ed-4f26-8e4c-952f8b9ac514",
  "id": "Content2_utils.removeQuizContent",
  "pluginId": "js-plugin",
  "pluginType": "JS",
  "unpublishedAction": {
    "actionConfiguration": {
      "encodeParamsToggle": true,
      "isAsync": true,
      "jsArguments": [],
      "paginationType": "NONE",
      "timeoutInMillisecond": 10000
    },
    "collectionId": "Content2_utils",
    "confirmBeforeExecute": false,
    "datasource": {
      "isAutoGenerated": false,
      "name": "UNUSED_DATASOURCE",
      "pluginId": "js-plugin"
    },
    "dynamicBindingPathList": [
      {
        "key": "body"
      }
    ],
    "executeOnLoad": false,
    "fullyQualifiedName": "utils.removeQuizContent",
    "name": "removeQuizContent",
    "pageId": "Content2",
    "userSetOnLoad": false
  }
}